digpipe/__init__.py
digpipe/__main__.py
digpipe/cli.py
digpipe/digtape.py
digpipe/mappers/__init__.py
digpipe/mappers/gba_tenkey.py
digpipe/pipeline.py
digpipe/sinks/__init__.py
digpipe/sinks/frame_log.py
digpipe/sources/__init__.py
digpipe/sources/pi_chudnovsky.py
digpipe/types.py
digpipe-1.1.2.dist-info/METADATA
digpipe-1.1.2.dist-info/WHEEL
digpipe-1.1.2.dist-info/entry_points.txt
digpipe-1.1.2.dist-info/RECORD
