Metadata-Version: 2.4
Name: digpipe
Version: 1.1.2
Summary: Decimal-Digit Input Pipeline
Author: DJ Stomp
Author-email: 85457381+DJStompZone@users.noreply.github.com
Requires-Python: >=3.10,<4.0
Classifier: Programming Language :: Python :: 3
Classifier: Programming Language :: Python :: 3.10
Classifier: Programming Language :: Python :: 3.11
Classifier: Programming Language :: Python :: 3.12
Classifier: Programming Language :: Python :: 3.13
Classifier: Programming Language :: Python :: 3.14
